README.txt
setup.cfg
setup.py
docs/HISTORY.txt
docs/LICENSE.GPL
docs/LICENSE.txt
qi/__init__.py
qi.jabberHelpdesk.egg-info/PKG-INFO
qi.jabberHelpdesk.egg-info/SOURCES.txt
qi.jabberHelpdesk.egg-info/dependency_links.txt
qi.jabberHelpdesk.egg-info/entry_points.txt
qi.jabberHelpdesk.egg-info/namespace_packages.txt
qi.jabberHelpdesk.egg-info/not-zip-safe
qi.jabberHelpdesk.egg-info/requires.txt
qi.jabberHelpdesk.egg-info/top_level.txt
qi/jabberHelpdesk/__init__.py
qi/jabberHelpdesk/configure.zcml
qi/jabberHelpdesk/interfaces.py
qi/jabberHelpdesk/tests.py
qi/jabberHelpdesk/upgrades.py
qi/jabberHelpdesk/upgrades.zcml
qi/jabberHelpdesk/version.txt
qi/jabberHelpdesk/browser/HelpdeskKSSView.py
qi/jabberHelpdesk/browser/__init__.py
qi/jabberHelpdesk/browser/agents.pt
qi/jabberHelpdesk/browser/agents.py
qi/jabberHelpdesk/browser/chat.pt
qi/jabberHelpdesk/browser/chatRequest.pt
qi/jabberHelpdesk/browser/chatRequest.py
qi/jabberHelpdesk/browser/chatView.py
qi/jabberHelpdesk/browser/configure.zcml
qi/jabberHelpdesk/browser/emoticons.py
qi/jabberHelpdesk/browser/fileDownload.py
qi/jabberHelpdesk/browser/helpdesk.py
qi/jabberHelpdesk/browser/helpdeskSettings.py
qi/jabberHelpdesk/browser/xmlrpc.py
qi/jabberHelpdesk/browser/portlets/__init__.py
qi/jabberHelpdesk/browser/portlets/configure.zcml
qi/jabberHelpdesk/browser/portlets/helpdeskPortlet.pt
qi/jabberHelpdesk/browser/portlets/helpdeskPortlet.py
qi/jabberHelpdesk/browser/resources/helpdesk.css
qi/jabberHelpdesk/browser/resources/helpdesk.gif
qi/jabberHelpdesk/browser/resources/corners/bl.png
qi/jabberHelpdesk/browser/resources/corners/br.png
qi/jabberHelpdesk/browser/resources/corners/tl.png
qi/jabberHelpdesk/browser/resources/corners/tr.png
qi/jabberHelpdesk/browser/resources/kss/helpdesk.kss
qi/jabberHelpdesk/browser/resources/kss/helpdeskportlet.kss
qi/jabberHelpdesk/browser/resources/smileys/smiley_cool.png
qi/jabberHelpdesk/browser/resources/smileys/smiley_lol.png
qi/jabberHelpdesk/browser/resources/smileys/smiley_sad.png
qi/jabberHelpdesk/browser/resources/smileys/smiley_skeptic.png
qi/jabberHelpdesk/browser/resources/smileys/smiley_smile.png
qi/jabberHelpdesk/browser/resources/smileys/smiley_surprised.png
qi/jabberHelpdesk/browser/resources/smileys/smiley_tongue.png
qi/jabberHelpdesk/browser/resources/smileys/smiley_wink.png
