Metadata-Version: 1.0
Name: qi.jabberHelpdesk
Version: 0.30
Summary: An online helpdesk product for plone
Home-page: http://github.com/ggozad/qi.jabberHelpdesk
Author: G. Gozadinos
Author-email: ggozad@qiweb.net
License: GPL
Keywords: plone,jabber,helpdesk
Platform: UNKNOWN
Classifier: Environment :: Web Environment
Classifier: Framework :: Plone
Classifier: Intended Audience :: Developers
Classifier: License :: OSI Approved :: GNU General Public License (GPL)
Classifier: Operating System :: OS Independent
Classifier: Programming Language :: Python
Classifier: Topic :: Software Development :: Libraries :: Python Modules
